paquetefe/__init__.py
paquetefe/de_classes/__init__.py
paquetefe/de_classes/countries_iso3166.csv
paquetefe/de_classes/currency_iso_4217_table.csv
paquetefe/de_classes/estructura_nodos_xml.csv
paquetefe/de_classes/eventos.py
paquetefe/de_classes/gen_xml.py
paquetefe/de_classes/geography_reference.py
paquetefe/de_classes/globals.py
paquetefe/de_classes/mysql_db_admin.py
paquetefe/de_classes/process_mysql.py
paquetefe/de_classes/referencia_geografica.csv
paquetefe/de_classes/settings.py
paquetefe/de_classes/signature_provider.py
paquetefe/de_classes/signature_providers/__init__.py
paquetefe/de_classes/signature_providers/cima/__init__.py
paquetefe/de_classes/signature_providers/cima/cima_service_client.py
paquetefe/de_classes/signature_providers/code100/__init__.py
paquetefe/de_classes/signature_providers/code100/code100_service_client.py
paquetefe/de_classes/signature_providers/factury/__init__.py
paquetefe/de_classes/signature_providers/factury/factury_service_client.py
paquetefe/de_classes/test_validate_xsd_eventos.py
paquetefe/de_classes/utils.py
paquetefe/de_classes/validaciones.txt
paquetefe/de_classes/validate.py
paquetefe/de_classes/vistas.py
paquetefe/de_classes/xml_namespace_local.xml
paquetefe/de_classes/xsd_files/DE_Types_v150.xsd
paquetefe/de_classes/xsd_files/DE_v150.xsd
paquetefe/de_classes/xsd_files/Departamentos_v141.xsd
paquetefe/de_classes/xsd_files/Evento_Types_v150.xsd
paquetefe/de_classes/xsd_files/Evento_v150.xsd
paquetefe/de_classes/xsd_files/Monedas_v150.xsd
paquetefe/de_classes/xsd_files/Paises_v100.xsd
paquetefe/de_classes/xsd_files/Unidades_Medida_v141.xsd
paquetefe/de_classes/xsd_files/__init__.py
paquetefe/de_classes/xsd_files/siRecepDE_v150.xsd
paquetefe/de_classes/xsd_files/siRecepEventoEmisor_v150.xsd
paquetefe/de_classes/xsd_files/siRecepEventoReceptor_v150.xsd
paquetefe/de_classes/xsd_files/siRecepEvento_v150.xsd
paquetefe/de_classes/xsd_files/xmldsig-core-schema.xsd
paquetefe/de_classes/xsd_sifen/DE_v150.xsd
paquete_fe-0.1.21.dist-info/METADATA
paquete_fe-0.1.21.dist-info/WHEEL
paquete_fe-0.1.21.dist-info/RECORD
