Metadata-Version: 2.1
Name: paquete-fe
Version: 0.1.21
Summary: Descripción de mi paquete
License: MIT
Author: Mateo Núñez
Author-email: mateo@idl.com.py
Requires-Python: >=3.8,<4.0
Classifier: License :: OSI Approved :: MIT License
Classifier: Programming Language :: Python :: 3
Classifier: Programming Language :: Python :: 3.8
Classifier: Programming Language :: Python :: 3.9
Classifier: Programming Language :: Python :: 3.10
Classifier: Programming Language :: Python :: 3.11
Requires-Dist: SQLAlchemy (>=2.0.6,<3.0.0)
Requires-Dist: lxml (>=4.9.2,<5.0.0)
Requires-Dist: pyOpenSSL (>=23.1.1,<24.0.0)
Requires-Dist: pytz (>=2022.7.1,<2023.0.0)
Requires-Dist: requests (>=2.28.2,<3.0.0)
Requires-Dist: zeep (>=4.2.1,<5.0.0)
